digital_marketing_portfolio-0.1.0.dist-info/licenses/LICENSE
src/__init__.py
src/app.py
src/static/css/style.css
src/static/js/main.js
src/templates/index.html
digital_marketing_portfolio-0.1.0.dist-info/METADATA
digital_marketing_portfolio-0.1.0.dist-info/WHEEL
digital_marketing_portfolio-0.1.0.dist-info/entry_points.txt
digital_marketing_portfolio-0.1.0.dist-info/top_level.txt
digital_marketing_portfolio-0.1.0.dist-info/RECORD
